<annotation>
	<folder>train</folder>
	<filename>4ade3729109e48e14e0e3126f49df099.jpg</filename>
	<path>C:\Users\Hi1pp\CTCI\Datasets\Example\images\train\4ade3729109e48e14e0e3126f49df099.jpg</path>
	<source>
		<database>Unknown</database>
	</source>
	<size>
		<width>564</width>
		<height>564</height>
		<depth>3</depth>
	</size>
	<segmented>0</segmented>
	<object>
		<name>Apple</name>
		<pose>Unspecified</pose>
		<truncated>0</truncated>
		<difficult>0</difficult>
		<bndbox>
			<xmin>105</xmin>
			<ymin>64</ymin>
			<xmax>477</xmax>
			<ymax>506</ymax>
		</bndbox>
	</object>
</annotation>
